embcomp.py
embcomp-0.1.2.dist-info/WHEEL
embcomp-0.1.2.dist-info/METADATA
embcomp-0.1.2.dist-info/RECORD
